MANIFEST.in
README.rst
setup.py
bin/googleanalytics
googleanalytics/__init__.py
googleanalytics/account.py
googleanalytics/blueprint.py
googleanalytics/columns.py
googleanalytics/errors.py
googleanalytics/query.py
googleanalytics/realtime.yml
googleanalytics/segments.py
googleanalytics.egg-info/PKG-INFO
googleanalytics.egg-info/SOURCES.txt
googleanalytics.egg-info/dependency_links.txt
googleanalytics.egg-info/requires.txt
googleanalytics.egg-info/top_level.txt
googleanalytics/auth/__init__.py
googleanalytics/auth/credentials.py
googleanalytics/auth/keyring.py
googleanalytics/auth/oauth.py
googleanalytics/commands/__init__.py
googleanalytics/commands/authorize.py
googleanalytics/commands/common.py
googleanalytics/commands/list.py
googleanalytics/commands/query.py
googleanalytics/commands/revoke.py
googleanalytics/commands/shell.py
googleanalytics/tests/__init__.py
googleanalytics/tests/base.py
googleanalytics/tests/meta.py
googleanalytics/tests/query.py
googleanalytics/tests/report.py
googleanalytics/utils/__init__.py
googleanalytics/utils/date.py
googleanalytics/utils/functional.py
googleanalytics/utils/server.py
googleanalytics/utils/string.py